jgram/__init__.py
jgram/context/__init__.py
jgram/context/context.py
jgram/exceptions.py
jgram/loader/__init__.py
jgram/loader/json_loader.py
jgram/loader/protocols.py
jgram/loader/tools.py
jgram/loggers.py
jgram/manager/__init__.py
jgram/manager/protocols.py
jgram/manager/windows_manager.py
jgram/registry/__init__.py
jgram/registry/handlers/__init__.py
jgram/registry/handlers/start.py
jgram/registry/handlers/update.py
jgram/registry/includer.py
jgram/registry/middleware.py
jgram/registry/protocols.py
jgram/registry/registry.py
jgram/storage/__init__.py
jgram/storage/memory.py
jgram/storage/protocols.py
jgram/window/__init__.py
jgram/window/markup/__init__.py
jgram/window/markup/markup.py
jgram/window/markup/tools.py
jgram/window/media/__init__.py
jgram/window/media/media.py
jgram/window/window.py
jgram-1.0.4b0.dist-info/LICENSE
jgram-1.0.4b0.dist-info/WHEEL
jgram-1.0.4b0.dist-info/METADATA
jgram-1.0.4b0.dist-info/RECORD
