Metadata-Version: 2.1
Name: jgram
Version: 1.0.4b0
Summary: Simple wrapper over aiogram for create bots structure in json files
Home-page: https://github.com/grehban/jgram
License: MIT
Keywords: telegram,bot,aiogram,api,wrapper,json,asyncio
Author: grehban
Author-email: maximfeedback19@gmail.com
Maintainer: grehban
Maintainer-email: maximfeedback19@gmail.com
Requires-Python: >=3.8,<4.0
Classifier: Environment :: Console
Classifier: Framework :: AIOgram
Classifier: Intended Audience :: Developers
Classifier: Intended Audience :: System Administrators
Classifier: License :: OSI Approved :: MIT License
Classifier: Programming Language :: Python :: 3
Classifier: Programming Language :: Python :: 3.10
Classifier: Programming Language :: Python :: 3.8
Classifier: Programming Language :: Python :: 3.9
Classifier: Topic :: Software Development :: Libraries :: Application Frameworks
Provides-Extra: fast
Provides-Extra: proxy
Requires-Dist: aiodns (>=3.0.0,<4.0.0); extra == "fast"
Requires-Dist: aiogram (>=2.21,<3.0)
Requires-Dist: aiohttp-socks (>=0.7.1,<0.8.0); extra == "proxy"
Requires-Dist: cchardet (>=2.1.7,<3.0.0); extra == "fast"
Requires-Dist: ujson (>=5.4.0,<6.0.0); extra == "fast"
Requires-Dist: uvloop (>=0.16.0,<0.17.0); (sys_platform == "darwin" or sys_platform == "linux") and (extra == "fast")
Project-URL: Repository, https://github.com/grehban/jgram
